{
	"1": ["Página p... ¡Se requiere una licencia Advanced!", "index.htm", []],
	"2": ["1. Intr... ¡Se requiere una licencia Advanced!", "introduccion.htm", []],
	"3": ["2. Mo... ¡Se requiere una licencia Advanced!", "modulos.htm", []],
	"4": ["2.1. Gestió... ¡Se requiere una licencia Advanced!", "gestion_de_areas_.htm", [2]],
	"5": ["2.2. Gestió... ¡Se requiere una licencia Advanced!", "gestion_de_libros_.htm", [2]],
	"6": ["2.2.1. Gestió... ¡Se requiere una licencia Advanced!", "gestion_de_usuarios_.htm", [2,5]],
	"7": ["2.3. Pr... ¡Se requiere una licencia Advanced!", "prestamos_.htm", [2]],
	"8": ["2.4. Devolucion... ¡Se requiere una licencia Advanced!", "devoluciones_y_sanciones_.htm", [2]],
	"9": ["4. Á... ¡Se requiere una licencia Advanced!", "4__areas.htm", []],
	"10": ["4.1 Consu... ¡Se requiere una licencia Advanced!", "4_1_consultar_area.htm", [3]],
	"11": ["4.2 Modif... ¡Se requiere una licencia Advanced!", "4_2_modificar_area.htm", [3]],
	"12": ["4.3 Elim... ¡Se requiere una licencia Advanced!", "4_3_eliminar_area.htm", [3]],
	"13": ["5. L... ¡Se requiere una licencia Advanced!", "5__libros.htm", [3]],
	"14": ["5.1 Consul... ¡Se requiere una licencia Advanced!", "5_1_consultar_libros.htm", [3,11]],
	"15": ["5.2  Modifi... ¡Se requiere una licencia Advanced!", "5_2__modificar_libros_.htm", [3,11]],
	"16": ["5.3 Elimin... ¡Se requiere una licencia Advanced!", "5_3_eliminar_libros_.htm", [3,11]],
	"17": ["Manual de... ¡Se requiere una licencia Advanced!", "manual_del_usuario.htm", [3,11,18]],
	"18": ["Mision, obje... ¡Se requiere una licencia Advanced!", "mision__objetivos_y_metas.htm", [3,11,18,23]],
	"19": ["Me... ¡Se requiere una licencia Advanced!", "menu.htm", [3,11,18,23]],
	"20": ["6. Pre... ¡Se requiere una licencia Advanced!", "6__prestamos_.htm", [3]],
	"21": ["6.1 Realizar... ¡Se requiere una licencia Advanced!", "6_1_realizar_devolucion_.htm", [3,12]],
	"22": ["7. San... ¡Se requiere una licencia Advanced!", "7__sanciones.htm", [3]],
	"23": ["8 Usu... ¡Se requiere una licencia Advanced!", "8_usuarios.htm", [3]],
	"24": ["8.1 Consul... ¡Se requiere una licencia Advanced!", "8_1_consultar_usuario.htm", [3,14]],
	"25": ["8.2 Modifi... ¡Se requiere una licencia Advanced!", "8_2_modificar_usuario.htm", [3,14]],
	"26": ["8.3 Elimin... ¡Se requiere una licencia Advanced!", "8_3_eliminar_usuario.htm", [3,14]]
}